rs232_to_tripplite/__init__.py
rs232_to_tripplite/__main__.py
rs232_to_tripplite/connectors/__init__.py
rs232_to_tripplite/connectors/conn_serial.py
rs232_to_tripplite/logging/__init__.py
rs232_to_tripplite/logging/loggingfactory.py
rs232_to_tripplite/parsers/__init__.py
rs232_to_tripplite/parsers/parse_base.py
rs232_to_tripplite/parsers/parse_kvmseq.py
rs232_to_tripplite/requests/__init__.py
rs232_to_tripplite/requests/basesnmpcmd.py
rs232_to_tripplite/requests/healthcheckcmd.py
rs232_to_tripplite/requests/powerchangecmd.py
rs232_to_tripplite/requests/snmpcmdrunner.py
rs232_to_tripplite/scheduler/__init__.py
rs232_to_tripplite/scheduler/sersnmpscheduler.py
rs232_to_tripplite_pdu-1.0.10.dist-info/LICENSE
rs232_to_tripplite_pdu-1.0.10.dist-info/METADATA
rs232_to_tripplite_pdu-1.0.10.dist-info/WHEEL
rs232_to_tripplite_pdu-1.0.10.dist-info/top_level.txt
rs232_to_tripplite_pdu-1.0.10.dist-info/RECORD
